{
  "notes": [
    {
      "content": "custom-hookit aivan mahtavia",
      "id": 1
    },
    {
      "content": "paras feature ikinä <3",
      "id": 2
    },
    {
      "content": "soemthig new ",
      "id": 3
    },
    {
      "content": "soemthig new ",
      "id": 4
    },
    {
      "content": "soemthig new ",
      "id": 5
    },
    {
      "content": "new stuffs ",
      "id": 6
    },
    {
      "content": "",
      "id": 7
    },
    {
      "content": "seomthing ",
      "id": 8
    },
    {
      "content": "soemthing very very new",
      "id": 9
    },
    {
      "content": "seomthign very very very new",
      "id": 10
    },
    {
      "content": "veryv fer eafsdf asf a",
      "id": 11
    },
    {
      "content": "fsdaifj;salkd fj;sklf j;sk",
      "id": 12
    },
    {
      "content": "",
      "id": 13
    },
    {
      "content": "dfafna klfajs lkfajs; flask a",
      "id": 14
    }
  ],
  "persons": [
    {
      "name": "mluukkai",
      "number": "040-5483923",
      "id": 1
    },
    {
      "name": "asdfasdfas",
      "number": "fdsafasfsdafa",
      "id": 2
    },
    {
      "name": "fnaksdfj ;lasfj ;laskf  fdsalfj a;sklj",
      "number": "5098234-5982-908520",
      "id": 3
    }
  ]
}